<?xml version="1.0" encoding="UTF-8"?>
<entity-mappings xmlns="http://java.sun.com/xml/ns/persistence/orm"
                 xmlns:xsi="http://www.w3.org/2001/XMLSchema-instance"
                 xsi:schemaLocation="http://java.sun.com/xml/ns/persistence/orm http://java.sun.com/xml/ns/persistence/orm_1_0.xsd"
                 version="1.0">

    <!-- TODO: VERIFICAR QUE NO HAGA FALTA EL MAPEO DE LAS ENTIDADES -->
    <!--	
    <entity class="com.cloudfoundry.tstracker.model.Cliente" />
    <entity class="com.cloudfoundry.tstracker.model.Consultoria" />
    <entity class="com.cloudfoundry.tstracker.model.Desarrollador" />
    <entity class="com.cloudfoundry.tstracker.model.LiderTecnico" />
    <entity class="com.cloudfoundry.tstracker.model.Proyecto" />
    <entity class="com.cloudfoundry.tstracker.model.Reporte" />
    <entity class="com.cloudfoundry.tstracker.model.Tarea" />
    <entity class="com.cloudfoundry.tstracker.model.Usuario" />
    <entity class="com.cloudfoundry.tstracker.model.Rol" />
    -->
</entity-mappings>